vmpooler_client/__init__.py
vmpooler_client/command_parser.py
vmpooler_client/conf_file.py
vmpooler_client/service.py
vmpooler_client/util.py
vmpooler_client/version.py
vmpooler_client/commands/__init__.py
vmpooler_client/commands/config.py
vmpooler_client/commands/lifetime.py
vmpooler_client/commands/token.py
vmpooler_client/commands/vm.py
vmpooler_client-3.1.0.data/scripts/vmpooler_client_app.py
vmpooler_client-3.1.0.data/scripts/vmpooler_client_script.py
vmpooler_client-3.1.0.dist-info/DESCRIPTION.rst
vmpooler_client-3.1.0.dist-info/METADATA
vmpooler_client-3.1.0.dist-info/RECORD
vmpooler_client-3.1.0.dist-info/WHEEL
vmpooler_client-3.1.0.dist-info/metadata.json
vmpooler_client-3.1.0.dist-info/top_level.txt
