Metadata-Version: 2.0
Name: vmpooler-client
Version: 3.1.0
Summary: Manage resources in the vmpooler service from the command-line.
Home-page: https://github.com/puppetlabs/vmpooler-client
Author: Ryan Gard
Author-email: ryan.gard@puppetlabs.com
License: UNKNOWN
Platform: UNKNOWN
Classifier: Development Status :: 5 - Production/Stable
Classifier: Intended Audience :: End Users/Desktop
Classifier: Topic :: Utilities
Classifier: License :: OSI Approved :: Apache Software License
Classifier: Programming Language :: Python :: 2
Classifier: Programming Language :: Python :: 2.7
